Workbook

Sheet Resumo Anual Consolidado
A1: NETFITS PLATAFORMA DIGITAL S.A. — ESTUDO DE CUSTOS DE TECNOLOGIA & FINOPS (2026 - 2030)
A2: Consolidado por Exercício Social (Out/26 a Dez/30 · 51 Meses de Operação) · Eficiência de Capital e FinOps
A4: Conta DRE / Família de Tecnologia & FinOps | B4: 2026 (3 meses) | C4: 2027 (12 meses) | D4: 2028 (12 meses) | E4: 2029 (12 meses) | F4: 2030 (12 meses) | G4: TOTAL ACUMULADO (51M) | H4: % da Receita Bruta | I4: Economia FinOps vs. Tradicional
A5: 1. Squad de Agentes de IA Autônomos (8 Agentes) | B5: =SUM('Projeção Mensal (51 Meses)'!B9:D9) | C5: =SUM('Projeção Mensal (51 Meses)'!E9:P9) | D5: =SUM('Projeção Mensal (51 Meses)'!Q9:AB9) | E5: =SUM('Projeção Mensal (51 Meses)'!AC9:AN9) | F5: =SUM('Projeção Mensal (51 Meses)'!AO9:AZ9) | G5: =SUM(B5:F5) | H5: =G5/$G$36 | I5: 5961395.4
A6: 1.1 Shop Recommender (Gemini Flash) | B6: =SUM('Projeção Mensal (51 Meses)'!B10:D10) | C6: =SUM('Projeção Mensal (51 Meses)'!E10:P10) | D6: =SUM('Projeção Mensal (51 Meses)'!Q10:AB10) | E6: =SUM('Projeção Mensal (51 Meses)'!AC10:AN10) | F6: =SUM('Projeção Mensal (51 Meses)'!AO10:AZ10) | G6: =SUM(B6:F6) | H6: =G6/$G$36 | I6: -
A7: 1.2 Algorithmic Feed Curator (Gemini Lite) | B7: =SUM('Projeção Mensal (51 Meses)'!B11:D11) | C7: =SUM('Projeção Mensal (51 Meses)'!E11:P11) | D7: =SUM('Projeção Mensal (51 Meses)'!Q11:AB11) | E7: =SUM('Projeção Mensal (51 Meses)'!AC11:AN11) | F7: =SUM('Projeção Mensal (51 Meses)'!AO11:AZ11) | G7: =SUM(B7:F7) | H7: =G7/$G$36 | I7: -
A8: 1.3 Sentinel Fraud Shield (Gemini Flash) | B8: =SUM('Projeção Mensal (51 Meses)'!B12:D12) | C8: =SUM('Projeção Mensal (51 Meses)'!E12:P12) | D8: =SUM('Projeção Mensal (51 Meses)'!Q12:AB12) | E8: =SUM('Projeção Mensal (51 Meses)'!AC12:AN12) | F8: =SUM('Projeção Mensal (51 Meses)'!AO12:AZ12) | G8: =SUM(B8:F8) | H8: =G8/$G$36 | I8: -
A9: 1.4 Accounting & Tax DRE Audit (Gemini Pro) | B9: =SUM('Projeção Mensal (51 Meses)'!B13:D13) | C9: =SUM('Projeção Mensal (51 Meses)'!E13:P13) | D9: =SUM('Projeção Mensal (51 Meses)'!Q13:AB13) | E9: =SUM('Projeção Mensal (51 Meses)'!AC13:AN13) | F9: =SUM('Projeção Mensal (51 Meses)'!AO13:AZ13) | G9: =SUM(B9:F9) | H9: =G9/$G$36 | I9: -
A10: 1.5 Omnichannel CS Concierge (Gemini Flash) | B10: =SUM('Projeção Mensal (51 Meses)'!B14:D14) | C10: =SUM('Projeção Mensal (51 Meses)'!E14:P14) | D10: =SUM('Projeção Mensal (51 Meses)'!Q14:AB14) | E10: =SUM('Projeção Mensal (51 Meses)'!AC14:AN14) | F10: =SUM('Projeção Mensal (51 Meses)'!AO14:AZ14) | G10: =SUM(B10:F10) | H10: =G10/$G$36 | I10: -
A11: 1.6 Partner & VIP Co-Pilot (Gemini Flash) | B11: =SUM('Projeção Mensal (51 Meses)'!B15:D15) | C11: =SUM('Projeção Mensal (51 Meses)'!E15:P15) | D11: =SUM('Projeção Mensal (51 Meses)'!Q15:AB15) | E11: =SUM('Projeção Mensal (51 Meses)'!AC15:AN15) | F11: =SUM('Projeção Mensal (51 Meses)'!AO15:AZ15) | G11: =SUM(B11:F11) | H11: =G11/$G$36 | I11: -
A12: 1.7 Wearables Telemetry & Sensor AI (Lite) | B12: =SUM('Projeção Mensal (51 Meses)'!B16:D16) | C12: =SUM('Projeção Mensal (51 Meses)'!E16:P16) | D12: =SUM('Projeção Mensal (51 Meses)'!Q16:AB16) | E12: =SUM('Projeção Mensal (51 Meses)'!AC16:AN16) | F12: =SUM('Projeção Mensal (51 Meses)'!AO16:AZ16) | G12: =SUM(B12:F12) | H12: =G12/$G$36 | I12: -
A13: 1.8 Executive BI & Insights Miner (Gemini Pro) | B13: =SUM('Projeção Mensal (51 Meses)'!B17:D17) | C13: =SUM('Projeção Mensal (51 Meses)'!E17:P17) | D13: =SUM('Projeção Mensal (51 Meses)'!Q17:AB17) | E13: =SUM('Projeção Mensal (51 Meses)'!AC17:AN17) | F13: =SUM('Projeção Mensal (51 Meses)'!AO17:AZ17) | G13: =SUM(B13:F13) | H13: =G13/$G$36 | I13: -
A14: 2. Infraestrutura de TI & Cloud (Compute & Edge) | B14: =SUM('Projeção Mensal (51 Meses)'!B18:D18) | C14: =SUM('Projeção Mensal (51 Meses)'!E18:P18) | D14: =SUM('Projeção Mensal (51 Meses)'!Q18:AB18) | E14: =SUM('Projeção Mensal (51 Meses)'!AC18:AN18) | F14: =SUM('Projeção Mensal (51 Meses)'!AO18:AZ18) | G14: =SUM(B14:F14) | H14: =G14/$G$36 | I14: 598467
A15: 2.1 Compute Serverless & Containers (Cloud Run CUD) | B15: =SUM('Projeção Mensal (51 Meses)'!B19:D19) | C15: =SUM('Projeção Mensal (51 Meses)'!E19:P19) | D15: =SUM('Projeção Mensal (51 Meses)'!Q19:AB19) | E15: =SUM('Projeção Mensal (51 Meses)'!AC19:AN19) | F15: =SUM('Projeção Mensal (51 Meses)'!AO19:AZ19) | G15: =SUM(B15:F15) | H15: =G15/$G$36 | I15: -
A16: 2.2 Edge Computing, CDN & WAF (Cloudflare + GCS) | B16: =SUM('Projeção Mensal (51 Meses)'!B20:D20) | C16: =SUM('Projeção Mensal (51 Meses)'!E20:P20) | D16: =SUM('Projeção Mensal (51 Meses)'!Q20:AB20) | E16: =SUM('Projeção Mensal (51 Meses)'!AC20:AN20) | F16: =SUM('Projeção Mensal (51 Meses)'!AO20:AZ20) | G16: =SUM(B16:F16) | H16: =G16/$G$36 | I16: -
A17: 2.3 API Gateways, LB & DNS (Google Cloud LB) | B17: =SUM('Projeção Mensal (51 Meses)'!B21:D21) | C17: =SUM('Projeção Mensal (51 Meses)'!E21:P21) | D17: =SUM('Projeção Mensal (51 Meses)'!Q21:AB21) | E17: =SUM('Projeção Mensal (51 Meses)'!AC21:AN21) | F17: =SUM('Projeção Mensal (51 Meses)'!AO21:AZ21) | G17: =SUM(B17:F17) | H17: =G17/$G$36 | I17: -
A18: 3. Estrutura de Dados, Ledger & Analytics | B18: =SUM('Projeção Mensal (51 Meses)'!B22:D22) | C18: =SUM('Projeção Mensal (51 Meses)'!E22:P22) | D18: =SUM('Projeção Mensal (51 Meses)'!Q22:AB22) | E18: =SUM('Projeção Mensal (51 Meses)'!AC22:AN22) | F18: =SUM('Projeção Mensal (51 Meses)'!AO22:AZ22) | G18: =SUM(B18:F18) | H18: =G18/$G$36 | I18: 505139.77
A19: 3.1 Banco Relacional OLTP & Ledger (AlloyDB + PgBouncer) | B19: =SUM('Projeção Mensal (51 Meses)'!B23:D23) | C19: =SUM('Projeção Mensal (51 Meses)'!E23:P23) | D19: =SUM('Projeção Mensal (51 Meses)'!Q23:AB23) | E19: =SUM('Projeção Mensal (51 Meses)'!AC23:AN23) | F19: =SUM('Projeção Mensal (51 Meses)'!AO23:AZ23) | G19: =SUM(B19:F19) | H19: =G19/$G$36 | I19: -
A20: 3.2 Cache In-Memory & Redis (Upstash Redis) | B20: =SUM('Projeção Mensal (51 Meses)'!B24:D24) | C20: =SUM('Projeção Mensal (51 Meses)'!E24:P24) | D20: =SUM('Projeção Mensal (51 Meses)'!Q24:AB24) | E20: =SUM('Projeção Mensal (51 Meses)'!AC24:AN24) | F20: =SUM('Projeção Mensal (51 Meses)'!AO24:AZ24) | G20: =SUM(B20:F20) | H20: =G20/$G$36 | I20: -
A21: 3.3 Data Warehouse & Lakehouse (BigQuery / Iceberg) | B21: =SUM('Projeção Mensal (51 Meses)'!B25:D25) | C21: =SUM('Projeção Mensal (51 Meses)'!E25:P25) | D21: =SUM('Projeção Mensal (51 Meses)'!Q25:AB25) | E21: =SUM('Projeção Mensal (51 Meses)'!AC25:AN25) | F21: =SUM('Projeção Mensal (51 Meses)'!AO25:AZ25) | G21: =SUM(B21:F21) | H21: =G21/$G$36 | I21: -
A22: 3.4 Vector Database & Embeddings (Pgvector) | B22: =SUM('Projeção Mensal (51 Meses)'!B26:D26) | C22: =SUM('Projeção Mensal (51 Meses)'!E26:P26) | D22: =SUM('Projeção Mensal (51 Meses)'!Q26:AB26) | E22: =SUM('Projeção Mensal (51 Meses)'!AC26:AN26) | F22: =SUM('Projeção Mensal (51 Meses)'!AO26:AZ26) | G22: =SUM(B22:F22) | H22: =G22/$G$36 | I22: -
A23: 4. CRM, Comunicação & Mensageria Omnichannel | B23: =SUM('Projeção Mensal (51 Meses)'!B27:D27) | C23: =SUM('Projeção Mensal (51 Meses)'!E27:P27) | D23: =SUM('Projeção Mensal (51 Meses)'!Q27:AB27) | E23: =SUM('Projeção Mensal (51 Meses)'!AC27:AN27) | F23: =SUM('Projeção Mensal (51 Meses)'!AO27:AZ27) | G23: =SUM(B23:F23) | H23: =G23/$G$36 | I23: 193625.67
A24: 4.1 WhatsApp Business API Transacional (Meta API) | B24: =SUM('Projeção Mensal (51 Meses)'!B28:D28) | C24: =SUM('Projeção Mensal (51 Meses)'!E28:P28) | D24: =SUM('Projeção Mensal (51 Meses)'!Q28:AB28) | E24: =SUM('Projeção Mensal (51 Meses)'!AC28:AN28) | F24: =SUM('Projeção Mensal (51 Meses)'!AO28:AZ28) | G24: =SUM(B24:F24) | H24: =G24/$G$36 | I24: -
A25: 4.2 Push Notifications & Email (FCM + SendGrid) | B25: =SUM('Projeção Mensal (51 Meses)'!B29:D29) | C25: =SUM('Projeção Mensal (51 Meses)'!E29:P29) | D25: =SUM('Projeção Mensal (51 Meses)'!Q29:AB29) | E25: =SUM('Projeção Mensal (51 Meses)'!AC29:AN29) | F25: =SUM('Projeção Mensal (51 Meses)'!AO29:AZ29) | G25: =SUM(B25:F25) | H25: =G25/$G$36 | I25: -
A26: 4.3 Autenticação 2FA & SMS (Twilio + Firebase Auth) | B26: =SUM('Projeção Mensal (51 Meses)'!B30:D30) | C26: =SUM('Projeção Mensal (51 Meses)'!E30:P30) | D26: =SUM('Projeção Mensal (51 Meses)'!Q30:AB30) | E26: =SUM('Projeção Mensal (51 Meses)'!AC30:AN30) | F26: =SUM('Projeção Mensal (51 Meses)'!AO30:AZ30) | G26: =SUM(B26:F26) | H26: =G26/$G$36 | I26: -
A27: 5. Segurança, Observabilidade & Ferramentas FinOps | B27: =SUM('Projeção Mensal (51 Meses)'!B31:D31) | C27: =SUM('Projeção Mensal (51 Meses)'!E31:P31) | D27: =SUM('Projeção Mensal (51 Meses)'!Q31:AB31) | E27: =SUM('Projeção Mensal (51 Meses)'!AC31:AN31) | F27: =SUM('Projeção Mensal (51 Meses)'!AO31:AZ31) | G27: =SUM(B27:F27) | H27: =G27/$G$36 | I27: 184767.11
A28: 5.1 Observabilidade & APM (OpenTelemetry / Datadog) | B28: =SUM('Projeção Mensal (51 Meses)'!B32:D32) | C28: =SUM('Projeção Mensal (51 Meses)'!E32:P32) | D28: =SUM('Projeção Mensal (51 Meses)'!Q32:AB32) | E28: =SUM('Projeção Mensal (51 Meses)'!AC32:AN32) | F28: =SUM('Projeção Mensal (51 Meses)'!AO32:AZ32) | G28: =SUM(B28:F28) | H28: =G28/$G$36 | I28: -
A29: 5.2 Segurança, SSL, WAF & SecOps (Security Cmd Center) | B29: =SUM('Projeção Mensal (51 Meses)'!B33:D33) | C29: =SUM('Projeção Mensal (51 Meses)'!E33:P33) | D29: =SUM('Projeção Mensal (51 Meses)'!Q33:AB33) | E29: =SUM('Projeção Mensal (51 Meses)'!AC33:AN33) | F29: =SUM('Projeção Mensal (51 Meses)'!AO33:AZ33) | G29: =SUM(B29:F29) | H29: =G29/$G$36 | I29: -
A30: 💰 TOTAL TECNOLOGIA & FINOPS NETFITS | B30: =B5+B14+B18+B23+B27 | C30: =C5+C14+C18+C23+C27 | D30: =D5+D14+D18+D23+D27 | E30: =E5+E14+E18+E23+E27 | F30: =F5+F14+F18+F23+F27 | G30: =G5+G14+G18+G23+G27 | H30: =G30/$G$36 | I30: =SUM(I5, I14, I18, I23, I27) + 1100000
A31: (-) Subsídios Google Cloud Startup Program (Créditos de Nuvem & IA) | B31: =-B30 | C31: =-C30 | D31: 0 | E31: 0 | F31: 0 | G31: =SUM(B31:F31) | H31: =G31/$G$36 | I31: 1100000
A32: 💵 DESEMBOLSO LÍQUIDO EFETIVO DE CAIXA (NET CASH OPEX) | B32: =MAX(0, B30 + B31) | C32: =MAX(0, C30 + C31) | D32: =MAX(0, D30 + D31) | E32: =MAX(0, E30 + E31) | F32: =MAX(0, F30 + F31) | G32: =SUM(B32:F32) | H32: =G32/$G$36 | I32: =I30
A34: Base de Usuários Cadastrados (Pico do Exercício) | B34: 35000 | C34: 550000 | D34: 1500000 | E34: 2400000 | F34: 3000000 | G34: 3000000 | H34: - | I34: -
A35: Usuários Ativos Mensais (MAU Médio) | B35: 5600 | C35: 88000 | D35: 240000 | E35: 384000 | F35: 480000 | G35: 288000 | H35: - | I35: -
A36: Receita Bruta Projetada (R$) | B36: 451848 | C36: 29467545 | D36: 74015420 | E36: 103456890 | F36: 131058716 | G36: =SUM(B36:F36) | H36: - | I36: -
A37: Custo Médio Mensal de TI (R$ / mês) | B37: =B30/3 | C37: =C30/12 | D37: =D30/12 | E37: =E30/12 | F37: =F30/12 | G37: =G30/51 | H37: - | I37: -
A38: Custo Unitário de TI por Usuário Ativo (R$ / MAU / mês) | B38: =B37/B35 | C38: =C37/C35 | D38: =D37/D35 | E38: =E37/E35 | F38: =F37/F35 | G38: =G37/G35 | H38: - | I38: -
A39: Custo de TI sobre a Receita Bruta (%) | B39: =B30/B36 | C39: =C30/C36 | D39: =D30/D36 | E39: =E30/E36 | F39: =F30/F36 | G39: =G30/G36 | H39: - | I39: -

Sheet Projeção Mensal (51 Meses)
A1: NETFITS PLATAFORMA DIGITAL S.A. — DETALHAMENTO MENSAL DE CUSTOS DE TECNOLOGIA & FINOPS (OUT/26 A DEZ/30)
A2: Modelagem Financeira de Hiperescala (51 Meses) · Google Cloud Startup Program · Idempotência de Webhooks · Teto de Badges 50 NFs
A4: Conta DRE / Família FinOps | BA4: TOTAL (51M) | BB4: MÉDIA MENSAL
A5: Base de Usuários Cadastrados | B5: 0 | C5: 0 | D5: 0 | E5: 0 | F5: 0 | G5: 0 | H5: 0 | I5: 0 | J5: 0 | K5: 0 | L5: 0 | M5: 0 | N5: 0 | O5: 0 | P5: 0 | Q5: 0 | R5: 0 | S5: 0 | T5: 0 | U5: 0 | V5: 0 | W5: 0 | X5: 0 | Y5: 0 | Z5: 0 | AA5: 0 | AB5: 0 | AC5: 0 | AD5: 0 | AE5: 0 | AF5: 0 | AG5: 0 | AH5: 0 | AI5: 0 | AJ5: 0 | AK5: 0 | AL5: 0 | AM5: 0 | AN5: 0 | AO5: 0 | AP5: 0 | AQ5: 0 | AR5: 0 | AS5: 0 | AT5: 0 | AU5: 0 | AV5: 0 | AW5: 0 | AX5: 0 | AY5: 0 | AZ5: 0 | BA5: =AZ5 | BB5: =AVERAGE(B5:AZ5)
A6: Usuários Ativos Mensais (MAU Estimado) | B6: 100 | C6: 100 | D6: 160 | E6: 213 | F6: 280 | G6: 800 | H6: 2400 | I6: 8000 | J6: 16000 | K6: 32000 | L6: 80000 | M6: 120000 | N6: 140000 | O6: 152000 | P6: 160000 | Q6: 176000 | R6: 192000 | S6: 208000 | T6: 224000 | U6: 240000 | V6: 256000 | W6: 268000 | X6: 280000 | Y6: 292000 | Z6: 302400 | AA6: 312000 | AB6: 320000 | AC6: 328000 | AD6: 336000 | AE6: 344000 | AF6: 352000 | AG6: 360000 | AH6: 368000 | AI6: 376000 | AJ6: 384000 | AK6: 392000 | AL6: 400000 | AM6: 408000 | AN6: 416000 | AO6: 424000 | AP6: 432000 | AQ6: 440000 | AR6: 448000 | AS6: 456000 | AT6: 464000 | AU6: 472000 | AV6: 480000 | AW6: 480000 | AX6: 480000 | AY6: 480000 | AZ6: 480000 | BA6: =AZ6 | BB6: =AVERAGE(B6:AZ6)
A7: Receita Bruta Projetada (R$) | B7: 60 | C7: 297 | D7: 588.06 | E7: 2262.3401 | F7: 2925.0508 | G7: 8891.7819 | H7: 27993.129 | I7: 96873.826 | J7: 199431.78 | K7: 557724.62 | L7: 1411024.2 | M7: 2134533.4 | N7: 2553583.7 | O7: 2780812.4 | P7: 2929886.6 | Q7: 4018419.3 | R7: 4440295.1 | S7: 4869878.9 | T7: 5306493.3 | U7: 5749431 | V7: 6197966.5 | W7: 6553550.8 | X7: 6911421.5 | Y7: 7271004.9 | Z7: 7591576.4 | AA7: 7891919.5 | AB7: 8276840.4 | AC7: 8662880.5 | AD7: 9049275.8 | AE7: 9435305.3 | AF7: 9689584.9 | AG7: 9809049.9 | AH7: 9923654.1 | AI7: 10033588 | AJ7: 10139040 | AK7: 10240194 | AL7: 10337233 | AM7: 10430335 | AN7: 10519674 | AO7: 10605420 | AP7: 10687739 | AQ7: 10766792 | AR7: 10842736 | AS7: 10915723 | AT7: 10985900 | AU7: 11053410 | AV7: 11118390 | AW7: 10997680 | AX7: 10878669 | AY7: 10761395 | AZ7: 10997680 | BA7: =SUM(B7:AZ7) | BB7: =AVERAGE(B7:AZ7)
A9: 1. Squad de Agentes de IA Autônomos (8 Agentes) | B9: =SUM(B10:B17) | C9: =SUM(C10:C17) | D9: =SUM(D10:D17) | E9: =SUM(E10:E17) | F9: =SUM(F10:F17) | G9: =SUM(G10:G17) | H9: =SUM(H10:H17) | I9: =SUM(I10:I17) | ... BB9: =SUM(BB10:BB17)
A10: 1.1 Shop Recommender (Gemini Flash) | B10: 11.84 | C10: 45 | D10: 114.45 | E10: 171.09 | F10: 216.44 | G10: 255.75 | H10: 273.83 | I10: 291.08 | J10: 307.63 | K10: 323.55 | L10: 353.81 | M10: 382.3 | N10: 409.33 | O10: 435.13 | P10: 442.1 | Q10: 448.99 | R10: 455.8 | S10: 462.55 | T10: 469.22 | U10: 475.82 | V10: 482.36 | W10: 488.83 | X10: 495.25 | Y10: 501.6 | Z10: 507.9 | AA10: 514.14 | AB10: 520.32 | AC10: 526.46 | AD10: 532.54 | AE10: 538.57 | AF10: 544.55 | AG10: 550.49 | AH10: 556.38 | AI10: 562.22 | AJ10: 568.02 | AK10: 573.78 | AL10: 579.5 | AM10: 585.18 | AN10: 590.81 | AO10: 596.41 | AP10: 601.97 | AQ10: 607.5 | AR10: 612.98 | AS10: 618.44 | AT10: 623.85 | AU10: 629.24 | AV10: 634.59 | AW10: 639.91 | AX10: 645.19 | AY10: 650.45 | AZ10: 655.75 | BA10: =SUM(B10:AZ10) | BB10: =AVERAGE(B10:AZ10)
A11: 1.2 Algorithmic Feed Curator (Gemini Lite) | B11: 8.46 | C11: 30 | D11: 72.7 | E11: 106.44 | F11: 133.04 | G11: 155.84 | H11: 166.27 | I11: 176.19 | J11: 185.68 | K11: 194.78 | L11: 212.01 | M11: 228.17 | N11: 243.44 | O11: 257.96 | P11: 261.88 | Q11: 265.75 | R11: 269.57 | S11: 273.35 | T11: 277.09 | U11: 280.79 | V11: 284.44 | W11: 288.06 | X11: 291.65 | Y11: 295.19 | Z11: 298.7 | AA11: 302.18 | AB11: 305.63 | AC11: 309.05 | AD11: 312.43 | AE11: 315.78 | AF11: 319.11 | AG11: 322.41 | AH11: 325.68 | AI11: 328.92 | AJ11: 332.14 | AK11: 335.33 | AL11: 338.5 | AM11: 341.64 | AN11: 344.76 | AO11: 347.86 | AP11: 350.93 | AQ11: 353.99 | AR11: 357.02 | AS11: 360.03 | AT11: 363.02 | AU11: 365.99 | AV11: 368.94 | AW11: 371.87 | AX11: 374.78 | AY11: 377.68 | AZ11: 380.6 | BA11: =SUM(B11:AZ11) | BB11: =AVERAGE(B11:AZ11)
A12: 1.3 Sentinel Fraud Shield (Gemini Flash) | B12: 10 | C12: 38 | D12: 96.65 | E12: 144.47 | F12: 182.77 | G12: 215.96 | H12: 231.23 | I12: 245.8 | J12: 259.77 | K12: 273.22 | L12: 298.77 | M12: 322.83 | N12: 345.66 | O12: 367.44 | P12: 373.33 | Q12: 379.15 | R12: 384.9 | S12: 390.59 | T12: 396.23 | U12: 401.8 | V12: 407.33 | W12: 412.79 | X12: 418.21 | Y12: 423.58 | Z12: 428.89 | AA12: 434.16 | AB12: 439.38 | AC12: 444.56 | AD12: 449.7 | AE12: 454.79 | AF12: 459.84 | AG12: 464.86 | AH12: 469.83 | AI12: 474.77 | AJ12: 479.67 | AK12: 484.53 | AL12: 489.36 | AM12: 494.15 | AN12: 498.91 | AO12: 503.64 | AP12: 508.33 | AQ12: 513 | AR12: 517.63 | AS12: 522.24 | AT12: 526.81 | AU12: 531.36 | AV12: 535.87 | AW12: 540.37 | AX12: 544.83 | AY12: 549.27 | AZ12: 553.75 | BA12: =SUM(B12:AZ12) | BB12: =AVERAGE(B12:AZ12)
A13: 1.4 Accounting & Tax DRE Audit (Gemini Pro) | B13: 14.23 | C13: 45 | D13: 100.62 | E13: 142.3 | F13: 174.28 | G13: 201.25 | H13: 213.45 | I13: 225 | J13: 235.98 | K13: 246.48 | L13: 266.22 | M13: 284.6 | N13: 301.87 | O13: 318.2 | P13: 322.59 | Q13: 326.92 | R13: 331.19 | S13: 335.41 | T13: 339.58 | U13: 343.69 | V13: 347.76 | W13: 351.78 | X13: 355.76 | Y13: 359.69 | Z13: 363.58 | AA13: 367.42 | AB13: 371.23 | AC13: 375 | AD13: 378.73 | AE13: 382.43 | AF13: 386.09 | AG13: 389.71 | AH13: 393.3 | AI13: 396.86 | AJ13: 400.39 | AK13: 403.89 | AL13: 407.35 | AM13: 410.79 | AN13: 414.2 | AO13: 417.58 | AP13: 420.94 | AQ13: 424.26 | AR13: 427.57 | AS13: 430.84 | AT13: 434.09 | AU13: 437.32 | AV13: 440.53 | AW13: 443.71 | AX13: 446.86 | AY13: 450 | AZ13: 453.16 | BA13: =SUM(B13:AZ13) | BB13: =AVERAGE(B13:AZ13)
A14: 1.5 Omnichannel CS Concierge (Gemini Flash) | B14: 10 | C14: 38 | D14: 96.65 | E14: 144.47 | F14: 182.77 | G14: 215.96 | H14: 231.23 | I14: 245.8 | J14: 259.77 | K14: 273.22 | L14: 298.77 | M14: 322.83 | N14: 345.66 | O14: 367.44 | P14: 373.33 | Q14: 379.15 | R14: 384.9 | S14: 390.59 | T14: 396.23 | U14: 401.8 | V14: 407.33 | W14: 412.79 | X14: 418.21 | Y14: 423.58 | Z14: 428.89 | AA14: 434.16 | AB14: 439.38 | AC14: 444.56 | AD14: 449.7 | AE14: 454.79 | AF14: 459.84 | AG14: 464.86 | AH14: 469.83 | AI14: 474.77 | AJ14: 479.67 | AK14: 484.53 | AL14: 489.36 | AM14: 494.15 | AN14: 498.91 | AO14: 503.64 | AP14: 508.33 | AQ14: 513 | AR14: 517.63 | AS14: 522.24 | AT14: 526.81 | AU14: 531.36 | AV14: 535.87 | AW14: 540.37 | AX14: 544.83 | AY14: 549.27 | AZ14: 553.75 | BA14: =SUM(B14:AZ14) | BB14: =AVERAGE(B14:AZ14)
A15: 1.6 Partner & VIP Co-Pilot (Gemini Flash) | B15: 6.04 | C15: 20 | D15: 46.18 | E15: 66.23 | F15: 81.77 | G15: 94.97 | H15: 100.96 | I15: 106.65 | J15: 112.07 | K15: 117.26 | L15: 127.04 | M15: 136.18 | N15: 144.78 | O15: 152.93 | P15: 155.13 | Q15: 157.29 | R15: 159.43 | S15: 161.54 | T15: 163.63 | U15: 165.69 | V15: 167.73 | W15: 169.75 | X15: 171.75 | Y15: 173.72 | Z15: 175.67 | AA15: 177.61 | AB15: 179.52 | AC15: 181.42 | AD15: 183.3 | AE15: 185.16 | AF15: 187 | AG15: 188.83 | AH15: 190.64 | AI15: 192.43 | AJ15: 194.21 | AK15: 195.97 | AL15: 197.72 | AM15: 199.46 | AN15: 201.18 | AO15: 202.89 | AP15: 204.59 | AQ15: 206.27 | AR15: 207.94 | AS15: 209.59 | AT15: 211.24 | AU15: 212.87 | AV15: 214.5 | AW15: 216.11 | AX15: 217.71 | AY15: 219.3 | AZ15: 220.9 | BA15: =SUM(B15:AZ15) | BB15: =AVERAGE(B15:AZ15)
A16: 1.7 Wearables Telemetry & Sensor AI (Lite) | B16: 4.53 | C16: 15 | D16: 34.64 | E16: 49.67 | F16: 61.33 | G16: 71.22 | H16: 75.72 | I16: 79.99 | J16: 84.05 | K16: 87.94 | L16: 95.28 | M16: 102.13 | N16: 108.58 | O16: 114.7 | P16: 116.34 | Q16: 117.97 | R16: 119.57 | S16: 121.16 | T16: 122.72 | U16: 124.27 | V16: 125.8 | W16: 127.31 | X16: 128.81 | Y16: 130.29 | Z16: 131.76 | AA16: 133.21 | AB16: 134.64 | AC16: 136.06 | AD16: 137.47 | AE16: 138.87 | AF16: 140.25 | AG16: 141.62 | AH16: 142.98 | AI16: 144.32 | AJ16: 145.66 | AK16: 146.98 | AL16: 148.29 | AM16: 149.59 | AN16: 150.89 | AO16: 152.17 | AP16: 153.44 | AQ16: 154.7 | AR16: 155.95 | AS16: 157.2 | AT16: 158.43 | AU16: 159.66 | AV16: 160.87 | AW16: 162.08 | AX16: 163.28 | AY16: 164.47 | AZ16: 165.67 | BA16: =SUM(B16:AZ16) | BB16: =AVERAGE(B16:AZ16)
A17: 1.8 Executive BI & Insights Miner (Gemini Pro) | B17: 6.62 | C17: 20 | D17: 43.3 | E17: 60.4 | F17: 73.38 | G17: 84.24 | H17: 89.14 | I17: 93.77 | J17: 98.15 | K17: 102.34 | L17: 110.2 | M17: 117.49 | N17: 124.33 | O17: 130.78 | P17: 132.51 | Q17: 134.22 | R17: 135.9 | S17: 137.56 | T17: 139.2 | U17: 140.82 | V17: 142.42 | W17: 144 | X17: 145.56 | Y17: 147.11 | Z17: 148.63 | AA17: 150.14 | AB17: 151.64 | AC17: 153.11 | AD17: 154.58 | AE17: 156.02 | AF17: 157.46 | AG17: 158.88 | AH17: 160.28 | AI17: 161.67 | AJ17: 163.05 | AK17: 164.42 | AL17: 165.78 | AM17: 167.12 | AN17: 168.45 | AO17: 169.77 | AP17: 171.08 | AQ17: 172.38 | AR17: 173.66 | AS17: 174.94 | AT17: 176.21 | AU17: 177.47 | AV17: 178.71 | AW17: 179.95 | AX17: 181.18 | AY17: 182.4 | AZ17: 183.63 | BA17: =SUM(B17:AZ17) | BB17: =AVERAGE(B17:AZ17)
A18: 2. Infraestrutura de TI & Cloud (Compute & Edge) | B18: =SUM(B19:B21) | C18: =SUM(C19:C21) | D18: =SUM(D19:D21) | E18: =SUM(E19:E21) | F18: =SUM(F19:F21) | G18: =SUM(G19:G21) | H18: =SUM(H19:H21) | I18: =SUM(I19:I21) | ... BB18: =SUM(BB19:BB21)
A19: 2.1 Compute Serverless & Containers (Cloud Run CUD) | B19: 69.68 | C19: 382.92 | D19: 1259.93 | E19: 2104.3 | F19: 2840.64 | G19: 3514.55 | H19: 3834.63 | I19: 4145.56 | J19: 4448.51 | K19: 4744.36 | L19: 5317.63 | M19: 5869.92 | N19: 6404.5 | O19: 6923.82 | P19: 7065.64 | Q19: 7206.46 | R19: 7346.32 | S19: 7485.26 | T19: 7623.28 | U19: 7760.44 | V19: 7896.75 | W19: 8032.24 | X19: 8166.94 | Y19: 8300.86 | Z19: 8434.02 | AA19: 8566.45 | AB19: 8698.16 | AC19: 8829.16 | AD19: 8959.5 | AE19: 9089.17 | AF19: 9218.2 | AG19: 9346.59 | AH19: 9474.37 | AI19: 9601.55 | AJ19: 9728.13 | AK19: 9854.14 | AL19: 9979.58 | AM19: 10104.48 | AN19: 10228.83 | AO19: 10352.66 | AP19: 10475.96 | AQ19: 10598.76 | AR19: 10721.07 | AS19: 10842.88 | AT19: 10964.21 | AU19: 11085.07 | AV19: 11205.47 | AW19: 11325.42 | AX19: 11444.93 | AY19: 11564 | AZ19: 11684.31 | BA19: =SUM(B19:AZ19) | BB19: =AVERAGE(B19:AZ19)
A20: 2.2 Edge Computing, CDN & WAF (Cloudflare + GCS) | B20: 23.23 | C20: 127.68 | D20: 420.11 | E20: 701.65 | F20: 947.18 | G20: 1171.89 | H20: 1278.61 | I20: 1382.29 | J20: 1483.3 | K20: 1581.95 | L20: 1773.1 | M20: 1957.25 | N20: 2135.5 | O20: 2308.66 | P20: 2355.95 | Q20: 2402.91 | R20: 2449.54 | S20: 2495.87 | T20: 2541.89 | U20: 2587.62 | V20: 2633.08 | W20: 2678.25 | X20: 2723.17 | Y20: 2767.82 | Z20: 2812.22 | AA20: 2856.38 | AB20: 2900.29 | AC20: 2943.98 | AD20: 2987.44 | AE20: 3030.67 | AF20: 3073.7 | AG20: 3116.51 | AH20: 3159.11 | AI20: 3201.52 | AJ20: 3243.73 | AK20: 3285.74 | AL20: 3327.57 | AM20: 3369.21 | AN20: 3410.68 | AO20: 3451.97 | AP20: 3493.08 | AQ20: 3534.03 | AR20: 3574.81 | AS20: 3615.43 | AT20: 3655.88 | AU20: 3696.18 | AV20: 3736.33 | AW20: 3776.32 | AX20: 3816.17 | AY20: 3855.87 | AZ20: 3895.98 | BA20: =SUM(B20:AZ20) | BB20: =AVERAGE(B20:AZ20)
A21: 2.3 API Gateways, LB & DNS (Google Cloud LB) | B21: 18.6 | C21: 85 | D21: 245.89 | E21: 388.52 | F21: 507.74 | G21: 613.9 | H21: 663.53 | I21: 711.31 | J21: 757.49 | K21: 802.27 | L21: 888.19 | M21: 970.02 | N21: 1048.43 | O21: 1123.93 | P21: 1144.44 | Q21: 1164.76 | R21: 1184.9 | S21: 1204.87 | T21: 1224.66 | U21: 1244.3 | V21: 1263.77 | W21: 1283.09 | X21: 1302.27 | Y21: 1321.29 | Z21: 1340.18 | AA21: 1358.94 | AB21: 1377.56 | AC21: 1396.05 | AD21: 1414.41 | AE21: 1432.65 | AF21: 1450.78 | AG21: 1468.79 | AH21: 1486.68 | AI21: 1504.47 | AJ21: 1522.15 | AK21: 1539.72 | AL21: 1557.19 | AM21: 1574.56 | AN21: 1591.83 | AO21: 1609.01 | AP21: 1626.09 | AQ21: 1643.08 | AR21: 1659.98 | AS21: 1676.79 | AT21: 1693.51 | AU21: 1710.15 | AV21: 1726.71 | AW21: 1743.19 | AX21: 1759.58 | AY21: 1775.9 | AZ21: 1792.37 | BA21: =SUM(B21:AZ21) | BB21: =AVERAGE(B21:AZ21)
A22: 3. Estrutura de Dados, Ledger & Analytics | B22: =SUM(B23:B26) | C22: =SUM(C23:C26) | D22: =SUM(D23:D26) | E22: =SUM(E23:E26) | F22: =SUM(F23:F26) | G22: =SUM(G23:G26) | H22: =SUM(H23:H26) | I22: =SUM(I23:I26) | ... BB22: =SUM(BB23:BB26)
A23: 3.1 Banco Relacional OLTP & Ledger (AlloyDB + PgBouncer) | B23: 51.1 | C23: 280.8 | D23: 923.92 | E23: 1543.11 | F23: 2083.07 | G23: 2577.27 | H23: 2811.98 | I23: 3039.99 | J23: 3262.15 | K23: 3479.1 | L23: 3899.49 | M23: 4304.49 | N23: 4696.5 | O23: 5077.32 | P23: 5181.32 | Q23: 5284.59 | R23: 5387.15 | S23: 5489.03 | T23: 5590.25 | U23: 5690.83 | V23: 5790.79 | W23: 5890.14 | X23: 5988.92 | Y23: 6087.12 | Z23: 6184.77 | AA23: 6281.88 | AB23: 6378.47 | AC23: 6474.54 | AD23: 6570.11 | AE23: 6665.2 | AF23: 6759.82 | AG23: 6853.97 | AH23: 6947.67 | AI23: 7040.93 | AJ23: 7133.76 | AK23: 7226.17 | AL23: 7318.15 | AM23: 7409.74 | AN23: 7500.93 | AO23: 7591.73 | AP23: 7682.15 | AQ23: 7772.21 | AR23: 7861.89 | AS23: 7951.22 | AT23: 8040.19 | AU23: 8128.82 | AV23: 8217.11 | AW23: 8305.07 | AX23: 8392.71 | AY23: 8480.02 | AZ23: 8568.24 | BA23: =SUM(B23:AZ23) | BB23: =AVERAGE(B23:AZ23)
A24: 3.2 Cache In-Memory & Redis (Upstash Redis) | B24: 9.3 | C24: 51.12 | D24: 168.2 | E24: 280.93 | F24: 379.23 | G24: 469.19 | H24: 511.92 | I24: 553.43 | J24: 593.88 | K24: 633.37 | L24: 709.91 | M24: 783.64 | N24: 855 | O24: 924.33 | P24: 943.27 | Q24: 962.07 | R24: 980.74 | S24: 999.29 | T24: 1017.71 | U24: 1036.02 | V24: 1054.22 | W24: 1072.31 | X24: 1090.29 | Y24: 1108.17 | Z24: 1125.95 | AA24: 1143.62 | AB24: 1161.21 | AC24: 1178.7 | AD24: 1196.1 | AE24: 1213.41 | AF24: 1230.63 | AG24: 1247.77 | AH24: 1264.83 | AI24: 1281.81 | AJ24: 1298.71 | AK24: 1315.53 | AL24: 1332.28 | AM24: 1348.95 | AN24: 1365.55 | AO24: 1382.08 | AP24: 1398.55 | AQ24: 1414.94 | AR24: 1431.27 | AS24: 1447.53 | AT24: 1463.73 | AU24: 1479.86 | AV24: 1495.94 | AW24: 1511.95 | AX24: 1527.9 | AY24: 1543.8 | AZ24: 1559.87 | BA24: =SUM(B24:AZ24) | BB24: =AVERAGE(B24:AZ24)
A25: 3.3 Data Warehouse & Lakehouse (BigQuery / Iceberg) | B25: 16.51 | C25: 95 | D25: 322.81 | E25: 546.67 | F25: 743.97 | G25: 925.78 | H25: 1012.47 | I25: 1096.88 | J25: 1179.28 | K25: 1259.9 | L25: 1416.5 | M25: 1567.79 | N25: 1714.61 | O25: 1857.55 | P25: 1896.64 | Q25: 1935.47 | R25: 1974.06 | S25: 2012.41 | T25: 2050.53 | U25: 2088.43 | V25: 2126.12 | W25: 2163.59 | X25: 2200.86 | Y25: 2237.93 | Z25: 2274.81 | AA25: 2311.5 | AB25: 2348.01 | AC25: 2384.34 | AD25: 2420.49 | AE25: 2456.48 | AF25: 2492.3 | AG25: 2527.96 | AH25: 2563.46 | AI25: 2598.81 | AJ25: 2634 | AK25: 2669.05 | AL25: 2703.95 | AM25: 2738.71 | AN25: 2773.33 | AO25: 2807.82 | AP25: 2842.17 | AQ25: 2876.39 | AR25: 2910.48 | AS25: 2944.45 | AT25: 2978.3 | AU25: 3012.02 | AV25: 3045.62 | AW25: 3079.11 | AX25: 3112.48 | AY25: 3145.75 | AZ25: 3179.38 | BA25: =SUM(B25:AZ25) | BB25: =AVERAGE(B25:AZ25)
A26: 3.4 Vector Database & Embeddings (Pgvector) | B26: 8 | C26: 45 | D26: 150.47 | E26: 253.05 | F26: 342.99 | G26: 425.58 | H26: 464.89 | I26: 503.12 | J26: 540.4 | K26: 576.84 | L26: 647.54 | M26: 715.74 | N26: 781.85 | O26: 846.14 | P26: 863.7 | Q26: 881.15 | R26: 898.49 | S26: 915.71 | T26: 932.83 | U26: 949.84 | V26: 966.75 | W26: 983.56 | X26: 1000.28 | Y26: 1016.91 | Z26: 1033.44 | AA26: 1049.89 | AB26: 1066.25 | AC26: 1082.53 | AD26: 1098.73 | AE26: 1114.85 | AF26: 1130.89 | AG26: 1146.85 | AH26: 1162.75 | AI26: 1178.57 | AJ26: 1194.32 | AK26: 1210 | AL26: 1225.61 | AM26: 1241.16 | AN26: 1256.64 | AO26: 1272.06 | AP26: 1287.41 | AQ26: 1302.71 | AR26: 1317.95 | AS26: 1333.13 | AT26: 1348.25 | AU26: 1363.31 | AV26: 1378.32 | AW26: 1393.27 | AX26: 1408.18 | AY26: 1423.02 | AZ26: 1438.02 | BA26: =SUM(B26:AZ26) | BB26: =AVERAGE(B26:AZ26)
A27: 4. CRM, Comunicação & Mensageria Omnichannel | B27: =SUM(B28:B30) | C27: =SUM(C28:C30) | D27: =SUM(D28:D30) | E27: =SUM(E28:E30) | F27: =SUM(F28:F30) | G27: =SUM(G28:G30) | H27: =SUM(H28:H30) | I27: =SUM(I28:I30) | ... BB27: =SUM(BB28:BB30)
A28: 4.1 WhatsApp Business API Transacional (Meta API) | B28: 9.51 | C28: 60 | D28: 217.43 | E28: 378.57 | F28: 523.63 | G28: 659.14 | H28: 724.26 | I28: 787.96 | J28: 850.39 | K28: 911.69 | L28: 1031.35 | M28: 1147.62 | N28: 1261.02 | O28: 1371.92 | P28: 1402.32 | Q28: 1432.56 | R28: 1462.64 | S28: 1492.57 | T28: 1522.34 | U28: 1551.97 | V28: 1581.47 | W28: 1610.82 | X28: 1640.04 | Y28: 1669.14 | Z28: 1698.1 | AA28: 1726.94 | AB28: 1755.67 | AC28: 1784.27 | AD28: 1812.76 | AE28: 1841.14 | AF28: 1869.42 | AG28: 1897.58 | AH28: 1925.64 | AI28: 1953.6 | AJ28: 1981.46 | AK28: 2009.22 | AL28: 2036.89 | AM28: 2064.46 | AN28: 2091.94 | AO28: 2119.33 | AP28: 2146.63 | AQ28: 2173.85 | AR28: 2200.98 | AS28: 2228.03 | AT28: 2254.99 | AU28: 2281.88 | AV28: 2308.68 | AW28: 2335.41 | AX28: 2362.07 | AY28: 2388.64 | AZ28: 2415.51 | BA28: =SUM(B28:AZ28) | BB28: =AVERAGE(B28:AZ28)
A29: 4.2 Push Notifications & Email (FCM + SendGrid) | B29: 6.49 | C29: 40 | D29: 142.64 | E29: 246.64 | F29: 339.76 | G29: 426.46 | H29: 468.04 | I29: 508.67 | J29: 548.44 | K29: 587.47 | L29: 663.55 | M29: 737.37 | N29: 809.28 | O29: 879.52 | P29: 898.77 | Q29: 917.9 | R29: 936.93 | S29: 955.86 | T29: 974.69 | U29: 993.42 | V29: 1012.06 | W29: 1030.61 | X29: 1049.07 | Y29: 1067.45 | Z29: 1085.74 | AA29: 1103.95 | AB29: 1122.08 | AC29: 1140.13 | AD29: 1158.1 | AE29: 1176.01 | AF29: 1193.84 | AG29: 1211.6 | AH29: 1229.29 | AI29: 1246.91 | AJ29: 1264.47 | AK29: 1281.96 | AL29: 1299.39 | AM29: 1316.76 | AN29: 1334.07 | AO29: 1351.32 | AP29: 1368.5 | AQ29: 1385.64 | AR29: 1402.71 | AS29: 1419.73 | AT29: 1436.7 | AU29: 1453.61 | AV29: 1470.48 | AW29: 1487.29 | AX29: 1504.05 | AY29: 1520.76 | AZ29: 1537.66 | BA29: =SUM(B29:AZ29) | BB29: =AVERAGE(B29:AZ29)
A30: 4.3 Autenticação 2FA & SMS (Twilio + Firebase Auth) | B30: 5.09 | C30: 30 | D30: 103.59 | E30: 176.65 | F30: 241.39 | G30: 301.24 | H30: 329.84 | I30: 357.71 | J30: 384.95 | K30: 411.63 | L30: 463.5 | M30: 513.7 | N30: 562.46 | O30: 610 | P30: 623 | Q30: 635.93 | R30: 648.78 | S30: 661.55 | T30: 674.25 | U30: 686.87 | V30: 699.43 | W30: 711.92 | X30: 724.35 | Y30: 736.71 | Z30: 749.02 | AA30: 761.26 | AB30: 773.44 | AC30: 785.56 | AD30: 797.63 | AE30: 809.65 | AF30: 821.61 | AG30: 833.52 | AH30: 845.39 | AI30: 857.2 | AJ30: 868.96 | AK30: 880.67 | AL30: 892.34 | AM30: 903.96 | AN30: 915.54 | AO30: 927.08 | AP30: 938.57 | AQ30: 950.02 | AR30: 961.43 | AS30: 972.8 | AT30: 984.13 | AU30: 995.42 | AV30: 1006.67 | AW30: 1017.89 | AX30: 1029.07 | AY30: 1040.21 | AZ30: 1051.47 | BA30: =SUM(B30:AZ30) | BB30: =AVERAGE(B30:AZ30)
A31: 5. Segurança, Observabilidade & Ferramentas FinOps | B31: =SUM(B32:B33) | C31: =SUM(C32:C33) | D31: =SUM(D32:D33) | E31: =SUM(E32:E33) | F31: =SUM(F32:F33) | G31: =SUM(G32:G33) | H31: =SUM(H32:H33) | I31: =SUM(I32:I33) | ... BB31: =SUM(BB32:BB33)
A32: 5.1 Observabilidade & APM (OpenTelemetry / Datadog) | B32: 13.65 | C32: 75 | D32: 246.77 | E32: 412.16 | F32: 556.38 | G32: 688.37 | H32: 751.06 | I32: 811.96 | J32: 871.3 | K32: 929.25 | L32: 1041.53 | M32: 1149.7 | N32: 1254.41 | O32: 1356.12 | P32: 1383.9 | Q32: 1411.48 | R32: 1438.88 | S32: 1466.09 | T32: 1493.12 | U32: 1519.99 | V32: 1546.68 | W32: 1573.22 | X32: 1599.6 | Y32: 1625.83 | Z32: 1651.92 | AA32: 1677.85 | AB32: 1703.65 | AC32: 1729.31 | AD32: 1754.84 | AE32: 1780.24 | AF32: 1805.51 | AG32: 1830.66 | AH32: 1855.68 | AI32: 1880.59 | AJ32: 1905.39 | AK32: 1930.07 | AL32: 1954.63 | AM32: 1979.1 | AN32: 2003.45 | AO32: 2027.71 | AP32: 2051.86 | AQ32: 2075.91 | AR32: 2099.86 | AS32: 2123.72 | AT32: 2147.49 | AU32: 2171.16 | AV32: 2194.74 | AW32: 2218.24 | AX32: 2241.64 | AY32: 2264.96 | AZ32: 2288.52 | BA32: =SUM(B32:AZ32) | BB32: =AVERAGE(B32:AZ32)
A33: 5.2 Segurança, SSL, WAF & SecOps (Security Cmd Center) | B33: 8.69 | C33: 50 | D33: 169.9 | E33: 287.72 | F33: 391.56 | G33: 487.25 | H33: 532.88 | I33: 577.3 | J33: 620.67 | K33: 663.1 | L33: 745.52 | M33: 825.16 | N33: 902.43 | O33: 977.66 | P33: 998.23 | Q33: 1018.67 | R33: 1038.98 | S33: 1059.16 | T33: 1079.23 | U33: 1099.17 | V33: 1119.01 | W33: 1138.73 | X33: 1158.35 | Y33: 1177.86 | Z33: 1197.27 | AA33: 1216.58 | AB33: 1235.8 | AC33: 1254.91 | AD33: 1273.94 | AE33: 1292.88 | AF33: 1311.74 | AG33: 1330.51 | AH33: 1349.19 | AI33: 1367.79 | AJ33: 1386.32 | AK33: 1404.76 | AL33: 1423.13 | AM33: 1441.43 | AN33: 1459.65 | AO33: 1477.8 | AP33: 1495.88 | AQ33: 1513.89 | AR33: 1531.83 | AS33: 1549.71 | AT33: 1567.52 | AU33: 1585.27 | AV33: 1602.96 | AW33: 1620.58 | AX33: 1638.15 | AY33: 1655.66 | AZ33: 1673.36 | BA33: =SUM(B33:AZ33) | BB33: =AVERAGE(B33:AZ33)
A34: 💰 TOTAL OPEX BRUTO DE TECNOLOGIA & FINOPS | B34: =B9+B18+B22+B27+B31 | C34: =C9+C18+C22+C27+C31 | D34: =D9+D18+D22+D27+D31 | E34: =E9+E18+E22+E27+E31 | F34: =F9+F18+F22+F27+F31 | G34: =G9+G18+G22+G27+G31 | H34: =H9+H18+H22+H27+H31 | I34: =I9+I18+I22+I27+I31 | ... BB34: =BB9+BB18+BB22+BB27+BB31
A35: (-) Créditos Google Cloud Startup Program (Subsídio de Nuvem & IA) | B35: =-B34 | C35: =-C34 | D35: =-D34 | E35: =-E34 | F35: =-F34 | G35: =-G34 | H35: =-H34 | I35: =-I34 | ... P35: =-P34 | Q35: 0 | R35: 0 | S35: 0 | T35: 0 | U35: 0 | V35: 0 | W35: 0 | X35: 0 | Y35: 0 | Z35: 0 | AA35: 0 | AB35: 0 | AC35: 0 | AD35: 0 | AE35: 0 | AF35: 0 | AG35: 0 | AH35: 0 | AI35: 0 | AJ35: 0 | AK35: 0 | AL35: 0 | AM35: 0 | AN35: 0 | AO35: 0 | AP35: 0 | AQ35: 0 | AR35: 0 | AS35: 0 | AT35: 0 | AU35: 0 | AV35: 0 | AW35: 0 | AX35: 0 | AY35: 0 | AZ35: 0 | BA35: =SUM(B35:AZ35) | BB35: =AVERAGE(B35:AZ35)
A36: 💵 DESEMBOLSO LÍQUIDO EFETIVO DE CAIXA (NET CASH OPEX) | B36: =MAX(0, B34 + B35) | C36: =MAX(0, C34 + C35) | D36: =MAX(0, D34 + D35) | E36: =MAX(0, E34 + E35) | F36: =MAX(0, F34 + F35) | G36: =MAX(0, G34 + G35) | H36: =MAX(0, H34 + H35) | I36: =MAX(0, I34 + I35) | ... BB36: =MAX(0, BB34 + BB35)
A38: 📊 Custo de TI por Usuário Ativo (R$ / MAU / mês) | B38: =B34/B6 | C38: =C34/C6 | D38: =D34/D6 | E38: =E34/E6 | F38: =F34/F6 | G38: =G34/G6 | H38: =H34/H6 | I38: =I34/I6 | ... BA38: =BA34/BA6 | BB38: =AVERAGE(B38:AZ38)
A39: 📈 Custo de TI sobre a Receita Bruta (%) | B39: =B34/B7 | C39: =C34/C7 | D39: =D34/D7 | E39: =E34/E7 | F39: =F34/F7 | G39: =G34/G7 | H39: =H34/H7 | I39: =I34/I7 | ... BA39: =BA34/BA7 | BB39: =AVERAGE(B39:AZ39)

Sheet Premissas & Arquitetura FinOps
A1: NETFITS PLATAFORMA DIGITAL S.A. — PREMISSAS TÉCNICAS E DIRETRIZES FINOPS (2026 - 2030)
A3: 1. Google Cloud Startup Program & Subsídios de Aceleração (2026 - 2027)
A4: • A Netfits é credenciada no Google Cloud Startup Program com pacote de até US$ 200.000 (R$ 1,1 Milhão) em créditos.
A5: • Desembolso efetivo de caixa em infraestrutura de nuvem é R$ 0,00 nos exercícios de 2026 e 2027.
A6: • Preserva 100% do capital de giro inicial para aquisição de usuários, parcerias e expansão comercial.
A7: • Acesso direto a especialistas de arquitetura do Google para validação de escalabilidade e segurança.
A9: 2. Idempotência Criptográfica de Webhooks Rock Encantech / MKPlace (/api/orders)
A10: • Validação de assinatura em tempo constante (crypto.timingSafeEqual) prevenindo timing attacks.
A11: • Upsert idempotente baseado no _id único do pedido com flag isReplay para ignorar notificações repetidas.
A12: • Cada transação física gera estritamente um crédito de cashback, prevenindo duplicidades em reenvios de status.
A13: • Reduz em mais de 60% as escritas no banco relacional e processamento serverless em picos de checkout.
A15: 3. Blindagem Atuarial do Passivo de Pontos (CPC 30 / IFRS 15) & Teto de Badges
... A41: • WhatsApp Business API restrito estritamente a 2FA, recuperação de senha crítica e saques de alta pontuação.
